{
  "customer_id": "cus-1002",
  "first_name": "Эммануил",
  "last_name": "Сорокина",
  "email": "bogdan_1994@example.com",
  "phone": "+78403056533",
  "birth_date": "1969-01-06",
  "gender": "male",
  "registration_date": "2025-09-23T19:57:10.925389",
  "is_loyalty_member": true,
  "loyalty_card_number": "LOYAL-C9106DA2DE",
  "purchase_location": {
    "store_id": "store-003",
    "store_name": "Большая Пикча — Магазин на пер. Л.Толстого",
    "store_network": "Большая Пикча",
    "store_type_description": "Супермаркет более 200 кв.м. Входит в сеть из 30 магазинов.",
    "country": "Россия",
    "city": "г. Вилюйск",
    "street": "ш. Моховое",
    "house": "323",
    "postal_code": "806043"
  },
  "delivery_address": {
    "country": "Россия",
    "city": "г. Вилюйск",
    "street": "бул. Революционный",
    "house": "972",
    "apartment": "98",
    "postal_code": "852736"
  },
  "preferences": {
    "preferred_language": "ru",
    "preferred_payment_method": "cash",
    "receive_promotions": true
  }
}